Metadata-Version: 2.1
Name: memoria-gui
Version: 0.1.3
Summary: GUI for memorizing vocabulary, grammar, phrases of a foreign language
Home-page: https://github.com/jeffjennings/memoria
Author: Jeff Jennings
Author-email: jjennings1519@gmail.com
License: LGPLv3
Project-URL: Bug Tracker, https://github.com/jeffjennings/memoria/issues
Keywords: language,Italian
Classifier: Development Status :: 3 - Alpha
Classifier: License :: OSI Approved :: GNU Lesser General Public License v3 (LGPLv3)
Classifier: Intended Audience :: Developers
Classifier: Intended Audience :: Science/Research
Classifier: Operating System :: MacOS :: MacOS X
Classifier: Operating System :: POSIX :: Linux
Classifier: Programming Language :: Python :: 3.9
Classifier: Programming Language :: Python :: 3.10
Classifier: Programming Language :: Python :: 3.11
Requires-Python: >=3.9
Provides-Extra: test
License-File: LICENSE.txt
